Metadata-Version: 2.1
Name: odoo12-addon-mail-activity-team
Version: 12.0.1.2.3
Summary: Add Teams to Activities
Home-page: https://github.com/OCA/social
Author: Eficent, Odoo Community Association (OCA)
Author-email: support@odoo-community.org
License: AGPL-3
Platform: UNKNOWN
Classifier: Programming Language :: Python
Classifier: Framework :: Odoo
Classifier: License :: OSI Approved :: GNU Affero General Public License v3
Classifier: Development Status :: 4 - Beta
Requires-Python: >=3.5
Requires-Dist: odoo12-addon-mail-activity-board
Requires-Dist: odoo (<12.1dev,>=12.0a)
